<?xml version = '1.0' encoding = 'UTF-8'?>
<TableProxyOraclev20c class="oracle.dbtools.crest.model.design.storage.oracle.v20c.TableProxyOraclev20c" name="Sales_Follow_Up" directorySegmentName="seg_1" id="6B90A7BB-2556-4FE5-4022-5F425D94346A">
<createdBy>PC</createdBy>
<createdTime>2023-08-19 12:52:11 UTC</createdTime>
<ownerDesignName>ch02_final_model</ownerDesignName>
<logging>YES</logging>
<partitionedRowMovement>DISABLE</partitionedRowMovement>
<temporaryChanged>false</temporaryChanged>
<accessDriverType>oracle_loader</accessDriverType>
<rejectLimit></rejectLimit>
<columnProxies itemClass="oracle.dbtools.crest.model.design.storage.oracle.v12c.ColumnProxyOraclev12c">
<ColumnProxy name="Comm_Event_Purpose_Type_ID" id="4E43B4AF-A16E-1D63-41A6-28B93BA71173">
<createdBy>PC</createdBy>
<createdTime>2023-08-19 12:52:11 UTC</createdTime>
<ownerDesignName>ch02_final_model</ownerDesignName>
</ColumnProxy>
<ColumnProxy name="Communication_Event_ID" id="9E7D316C-1C7C-7737-15AC-08D0A1E975DD">
<createdBy>PC</createdBy>
<createdTime>2023-08-19 12:52:11 UTC</createdTime>
<ownerDesignName>ch02_final_model</ownerDesignName>
</ColumnProxy>
</columnProxies>
<foreignKeys>
<ForeignKey class="oracle.dbtools.crest.model.design.storage.oracle.v10g.FKProxyOraclev10g" name="Sales_Follow_Up_COMMUNICATION_EVENT_PURPOSE_FK" id="58EF6AF1-D887-BA94-294C-A5FAB13B0826">
<createdBy>PC</createdBy>
<createdTime>2023-08-19 12:52:11 UTC</createdTime>
<ownerDesignName>ch02_final_model</ownerDesignName>
</ForeignKey>
</foreignKeys>
<primaryKeys>
<PrimaryKey class="oracle.dbtools.crest.model.design.storage.oracle.v10g.PKProxyOraclev10g" name="Sales_Follow_Up_PK" id="3E8B3858-44CE-D7B8-40FC-64492B3D16F7">
<createdBy>PC</createdBy>
<createdTime>2023-08-19 12:52:11 UTC</createdTime>
<ownerDesignName>ch02_final_model</ownerDesignName>
<indexSort>SORTED</indexSort>
</PrimaryKey>
</primaryKeys>
</TableProxyOraclev20c>
