<?xml version = '1.0' encoding = 'UTF-8'?>
<Relation class="oracle.dbtools.crest.model.design.logical.Relation" name="Relation_9" directorySegmentName="seg_0" id="E38FC7FD-290A-9D4D-C939-0D8D89E8D6D8">
<createdBy>user</createdBy>
<createdTime>2020-11-29 03:07:01 UTC</createdTime>
<ownerDesignName>Postal Address Information</ownerDesignName>
<engineerTo>
<item key="4487468B-1A4D-D9C6-04F3-2F8AA7701E2C" value="true"/>
</engineerTo>
<sourcePk>1C9E8F5F-F814-4B86-D6AF-E09544B62DAC</sourcePk>
<identifying>true</identifying>
<nameOnSource>Composed of</nameOnSource>
<nameOnTarget>within</nameOnTarget>
<optionalSource>true</optionalSource>
<optionalTarget>false</optionalTarget>
<sourceCardinality>1</sourceCardinality>
<sourceEntity>E92AA05E-E2D8-35F6-26E2-934C146CA0B2</sourceEntity>
<targetCardinalityString>*</targetCardinalityString>
<targetEntity>3EFCFBF3-D10E-D821-2734-E073719AB293</targetEntity>
<transferable>true</transferable>
<deleteRule>NO ACTION</deleteRule>
</Relation>